{
  "text": "Subchapter I. Definitions; Federally Regulated and Supervised Entities and Fannie Mae and Freddie Mac. | D.C. Law Library Skip to main content Toggle mobile menu Navigation D.C. Law Library Code of the District of Columbia Title 26. Banks and Other Financial Institutions. Chapter 11A. Home Loan Protection. Subchapter I. Definitions; Federally Regulated and Supervised Entities and Fannie Mae and Freddie Mac. Code of the District of Columbia Subchapter I. Definitions; Federally Regulated and Supervised Entities and Fannie Mae and Freddie Mac. \u00a7 26\u20131151.01. Definitions. \u00a7 26\u20131151.02. Federally regulated, supervised, and insured entities and the Federal National Mortgage Association and Federal Home Loan Corporation. Previous Chapter 11A. Home Loan Protection. Next Subchapter II. Prohibited Practices. The codes and laws on this website are in the public domain. Please do not scrape. Instead, bulk download the HTML or XML . Powered by the non-profit Open Law Library . Subchapter II. Prohibited Practices. | D.C. Law Library Skip to main content Toggle mobile menu Navigation D.C. Law Library Code of the District of Columbia Title 26. Banks and Other Financial Institutions. Chapter 11A. Home Loan Protection. Subchapter II. Prohibited Practices. Code of the District of Columbia Subchapter II. Prohibited Practices. \u00a7 26\u20131152.01. Applicability. \u00a7 26\u20131152.02. Insufficient repayment ability. \u00a7 26\u20131152.03. Restrictions on the financing of single-premium credit insurance. \u00a7 26\u20131152.04. Restriction on financing origination/discount points and fees. \u00a7 26\u20131152.05. No encouragement of default. \u00a7 26\u20131152.06. Unfair steering or improper use of credit scores. \u00a7 26\u20131152.07. Failing to report favorable payment record. \u00a7 26\u20131152.08. Home improvement contracts. \u00a7 26\u20131152.09. No increase in interest rate upon default. \u00a7 26\u20131152.10. Charges in bad faith. \u00a7 26\u20131152.11. Failure to timely send disclosure notice. \u00a7 26\u20131152.12. Prepayment premium, fee or charge. \u00a7 26\u20131152.13. Limitations on balloon payments. \u00a7 26\u20131152.14. No call provision. \u00a7 26\u20131152.15. No negative amortization. \u00a7 26\u20131152.16. No advance payments. \u00a7 26\u20131152.17. No advance waivers. \u00a7 26\u20131152.18. No oppressive mandatory arbitration clause. \u00a7 26\u20131152.19. Homeownership counseling. \u00a7 26\u20131152.20. Broker licensor. \u00a7 26\u20131152.21. Filing requirements. \u00a7 26\u20131152.22. Suspect settlement service providers. \u00a7 26\u20131152.23. Median family income. Previous Subchapter I. Definitions; Federally Regulated and Supervised Entities and Fannie Mae and Freddie Mac. Next Subchapter III. Violations and Remedies; Enforcement and Civil Liability. The codes and laws on this website are in the public domain. Please do not scrape. Instead, bulk download the HTML or XML . Powered by the non-profit Open Law Library . Subchapter III. Violations and Remedies; Enforcement and Civil Liability. | D.C. Law Library Skip to main content Toggle mobile menu Navigation D.C. Law Library Code of the District of Columbia Title 26. Banks and Other Financial Institutions. Chapter 11A. Home Loan Protection. Subchapter III. Violations and Remedies; Enforcement and Civil Liability. Code of the District of Columbia Subchapter III. Violations and Remedies; Enforcement and Civil Liability. \u00a7 26\u20131153.01. Violations and remedies. \u00a7 26\u20131153.02. Enforcement. \u00a7 26\u20131153.03. Administrative penalties. \u00a7 26\u20131153.04. Final decision. \u00a7 26\u20131153.05. Assignee liability. Previous Subchapter II. Prohibited Practices. Next Subchapter IV. Rulemaking. The codes and laws on this website are in the public domain. Please do not scrape. Instead, bulk download the HTML or XML . Powered by the non-profit Open Law Library . Subchapter IV. Rulemaking. | D.C. Law Library Skip to main content Toggle mobile menu Navigation D.C. Law Library Code of the District of Columbia Title 26. Banks and Other Financial Institutions. Chapter 11A. Home Loan Protection. Subchapter IV. Rulemaking. Code of the District of Columbia Subchapter IV. Rulemaking. \u00a7 26\u20131154.01. Rulemaking authority. Previous Subchapter III. Violations and Remedies; Enforcement and Civil Liability. Next Subchapter V. Applicability. The codes and laws on this website are in the public domain. Please do not scrape. Instead, bulk download the HTML or XML . Powered by the non-profit Open Law Library . Subchapter V. Applicability. | D.C. Law Library Skip to main content Toggle mobile menu Navigation D.C. Law Library Code of the District of Columbia Title 26. Banks and Other Financial Institutions. Chapter 11A. Home Loan Protection. Subchapter V. Applicability. Code of the District of Columbia Subchapter V. Applicability. \u00a7 26\u20131155.01. Applicability. Previous Subchapter IV. Rulemaking. Next Chapter 11B. Nationwide Mortgage Licensing System Conformity. The codes and laws on this website are in the public domain. Please do not scrape. Instead, bulk download the HTML or XML . Powered by the non-profit Open Law Library .",
  "metadata": {
    "site_url": "https://code.dccouncil.gov/us/dc/council/code/titles/26/chapters/11A",
    "extra_data": {
      "code_title": "Title 26: Banks and Other Financial Institutions",
      "chapter_number": "11A",
      "separated_text": {
        "Subchapter I. Definitions; Federally Regulated and Supervised Entities and Fannie Mae and Freddie Mac.": "\u00a7 26\u20131151.01. Definitions. \u00a7 26\u20131151.02. Federally regulated, supervised, and insured entities and the Federal National Mortgage Association and Federal Home Loan Corporation.",
        "Subchapter II. Prohibited Practices.": "\u00a7 26\u20131152.01. Applicability. \u00a7 26\u20131152.02. Insufficient repayment ability. \u00a7 26\u20131152.03. Restrictions on the financing of single-premium credit insurance. \u00a7 26\u20131152.04. Restriction on financing origination/discount points and fees. \u00a7 26\u20131152.05. No encouragement of default. \u00a7 26\u20131152.06. Unfair steering or improper use of credit scores. \u00a7 26\u20131152.07. Failing to report favorable payment record. \u00a7 26\u20131152.08. Home improvement contracts. \u00a7 26\u20131152.09. No increase in interest rate upon default. \u00a7 26\u20131152.10. Charges in bad faith. \u00a7 26\u20131152.11. Failure to timely send disclosure notice. \u00a7 26\u20131152.12. Prepayment premium, fee or charge. \u00a7 26\u20131152.13. Limitations on balloon payments. \u00a7 26\u20131152.14. No call provision. \u00a7 26\u20131152.15. No negative amortization. \u00a7 26\u20131152.16. No advance payments. \u00a7 26\u20131152.17. No advance waivers. \u00a7 26\u20131152.18. No oppressive mandatory arbitration clause. \u00a7 26\u20131152.19. Homeownership counseling. \u00a7 26\u20131152.20. Broker licensor. \u00a7 26\u20131152.21. Filing requirements. \u00a7 26\u20131152.22. Suspect settlement service providers. \u00a7 26\u20131152.23. Median family income.",
        "Subchapter III. Violations and Remedies; Enforcement and Civil Liability.": "\u00a7 26\u20131153.01. Violations and remedies. \u00a7 26\u20131153.02. Enforcement. \u00a7 26\u20131153.03. Administrative penalties. \u00a7 26\u20131153.04. Final decision. \u00a7 26\u20131153.05. Assignee liability.",
        "Subchapter IV. Rulemaking.": "\u00a7 26\u20131154.01. Rulemaking authority.",
        "Subchapter V. Applicability.": "\u00a7 26\u20131155.01. Applicability."
      }
    }
  }
}