{
  "text": "\u00a7 31\u20131501. Definitions. | D.C. Law Library Skip to main content Toggle mobile menu Navigation D.C. Law Library Code of the District of Columbia Title 31. Insurance and Securities. Chapter 15. Managing General Agents. \u00a7 31\u20131501. Definitions. Code of the District of Columbia \u00a7 31\u20131501. Definitions. For the purposes of this chapter, the term: (1) \u201cActuary\u201d means a person who is a member in good standing of the American Academy of Actuaries. (2) \u201cDistrict\u201d means the District of Columbia. (3) \u201cInsurer\u201d means any person, firm, association, or corporation duly licensed in the District as an insurance company pursuant to \u00a7\u00a7 31-4304 and 31-2502.02 . (4) (A) \u201cManaging general agent\u201d means any person, firm, association, or corporation who: (i) Negotiates and binds ceding reinsurance contracts on behalf of an insurer; or (ii) Manages all or part of the insurance business of an insurer, including the management of a separate division, department, or underwriting office; and (iii) Acts as an agent for such an insurer whether known as a managing general agent, manager, or other similar term, who, with or without the authority, either separately or together with affiliates, produces, directly or indirectly, and underwrites an amount of gross direct written premiums equal to or more than 5% of the policyholder surplus as reported in the last annual statement of the insurer in any one quarter or year, and, in addition, adjusts or pays claims in excess of an amount determined by the Mayor, or negotiates reinsurance on behalf of the insurer. (B) Notwithstanding the above definition, the term \u201cmanaging general agent\u201d shall not apply to the following persons for the purposes of this chapter: (i) An employee of the insurer; (ii) A United States manager of the United States branch of an alien insurer; (iii) An underwriting manager who, pursuant to contract, manages all or part of the insurance operations of the insurer, is under common control with the insurer, subject to Chapter 7 of this title , or its predecessor, and whose compensation is not based on the volume of premiums written; or (iv) The attorney-in-fact authorized by and acting for the subscribers of a reciprocal insurer or inter-insurance exchange under powers of attorney. (5) \u201cProducers\u201d means an insurance broker or brokers or any other person, firm, association, or corporation, when for any compensation, commission or other thing of value, such person, firm, association, or corporation acts or aids in any manner in soliciting, negotiating, or procuring the making of any insurance contract on behalf of an insured other than the person, firm, association, or corporation. (6) \u201cUnderwrite\u201d means the authority to accept or reject risks on behalf of the insurer. ( Oct. 21, 1993, D.C. Law 10-41, \u00a7 2, 40 DCR 6014 ; Apr. 18, 1996, D.C. Law 11-110, \u00a7 41, 43 DCR 530 .) Prior Codifications 1981 Ed., \u00a7\u200235-3001. Section References This section is referenced in \u00a7 31-1504 . Editor's Notes Mayor authorized to issue rules: Section 8 of D.C. Law 10-41 provided that the Mayor shall, pursuant to subchapter I of Chapter 15 of Title 1 subchapter I of Chapter 5 of Title 2 , 2001 Ed., issue rules to implement the provisions of this chapter. Delegation of Authority Delegation of authority pursuant to D.C. Law 10-41 , the Managing General Agents Act of 1993, see Mayor\u2019s Order 94-54, March 7, 1994 ( 41 DCR 1433). Previous Chapter 15. Managing General Agents. Next \u00a7 31\u20131502. Licensure. The codes and laws on this website are in the public domain. Please do not scrape. Instead, bulk download the HTML or XML . Powered by the non-profit Open Law Library . \u00a7 31\u20131502. Licensure. | D.C. Law Library Skip to main content Toggle mobile menu Navigation D.C. Law Library Code of the District of Columbia Title 31. Insurance and Securities. Chapter 15. Managing General Agents. \u00a7 31\u20131502. Licensure. Code of the District of Columbia \u00a7 31\u20131502. Licensure. (a) No person, firm, association, or corporation shall act in the capacity of a managing general agent with respect to risks located in the District for an insurer licensed in the District, unless the person is a licensed broker in the District. (b) No person, firm, association, or corporation shall act in the capacity of a managing general agent representing an insurer domiciled in the District with respect to risks located outside the District, nor shall an insurer utilize the services of such a managing general agent, unless the person is licensed as a broker in the District, which license may be a nonresident license, pursuant to the provisions of this chapter. (c) The Mayor may require a bond in an amount acceptable to him or her for the protection of the insurer. (d) The Mayor may require the managing general agent to maintain an errors and omissions policy. ( Oct. 21, 1993, D.C. Law 10-41, \u00a7 3, 40 DCR 6014 ; May 16, 1995, D.C. Law 10-255, \u00a7 29(a), 41 DCR 5193 .) Prior Codifications 1981 Ed., \u00a7\u200235-3002. Previous \u00a7 31\u20131501. Definitions. Next \u00a7 31\u20131503. Required contract provisions. The codes and laws on this website are in the public domain. Please do not scrape. Instead, bulk download the HTML or XML . Powered by the non-profit Open Law Library . \u00a7 31\u20131503. Required contract provisions. | D.C. Law Library Skip to main content Toggle mobile menu Navigation D.C. Law Library Code of the District of Columbia Title 31. Insurance and Securities. Chapter 15. Managing General Agents. \u00a7 31\u20131503. Required contract provisions. Code of the District of Columbia \u00a7 31\u20131503. Required contract provisions. No person, firm, association, or corporation acting in the capacity of a managing general agent shall place business with an insurer unless there is in force a written contract between the parties which sets forth the responsibilities of each party, and where both parties share responsibility for a particular function, specifies the division of the responsibilities, and which contains the following minimum provisions: (1) The insurer may terminate the contract for cause upon written notice to the managing general agent. The insurer may suspend the underwriting authority of the managing general agent during the pendency of any dispute regarding the cause for termination. (2) The managing general agent will render accounts to the insurer detailing all transactions and remit all funds due under the contract to the insurer on not less than a monthly basis. (3) All funds collected for the account of an insurer will be held in a separate account by the managing general agent in a fiduciary capacity in a bank which is a member of the Federal Reserve System. This account shall be used for all payments on behalf of the insurer. The managing general agent may retain no more than 3 months estimated claims payments and allocated loss adjustment expenses. (4) Separate records of business written by the managing general agent will be maintained. The insurer shall have access and right to copy all accounts and records related to its business in a form usable by the insurer, and the Mayor shall have access to all books, bank accounts, and records of the managing general agent in a form usable to the Mayor. These records shall be retained according to Chapter 14 of this title , and \u00a7\u00a7 31-4440 and 31-5204 . (5) The contract may not be assigned in whole or part by the managing general agent. (6) Appropriate underwriting guidelines are required, including: (A) The maximum annual premium volume; (B) The basis of the rates to be charged; (C) The types of risks which may be written; (D) Maximum limits of liability; (E) Applicable exclusions; (F) Territorial limitations; (G) Policy cancellation provisions; and (H) The maximum policy period. (7) The insurer shall have the right to cancel or not renew any policy of insurance subject to the applicable laws and regulations of the District governing the cancellation and nonrenewal of insurance policies. (8) If the contract permits the managing general agent to settle claims on behalf of the insurer: (A) All claims must be reported to the company within 48 hours of receipt. (B) A copy of the claim file will be sent to the insurer at its request or as soon as it becomes known that the claim: (i) Has the potential to exceed an amount determined by the Mayor or exceeds the limit set by the company, whichever is less; (ii) Involves a coverage dispute; (iii) May exceed the managing general agent\u2019s claims settlement authority; (iv) Is open for more than 6 months; or (v) Is closed by payment of an amount set by the Mayor or an amount set by the company, whichever is less. (C) All claim files will be the joint property of the insurer and managing general agent. Upon an order of liquidation of the insurer, however, these files shall become the sole property of the insurer or its estate; the managing general agent shall have reasonable access to and the right to copy the files on a timely basis. (D) Any settlement authority granted to the managing general agent may be terminated for cause upon the insurer\u2019s written notice to the managing general agent or upon the termination of the contract. The insurer may suspend the settlement authority during the pendency of any dispute regarding the cause for termination. (9) Where electronic claims files are in existence, the contract must address the timely transmission of the data. (10) If the contract provides for a sharing of interim profits by the managing general agent, and the managing general agent has the authority to determine the amount of the interim profits by establishing loss reserves or controlling claim payments, or in any other manner, interim profits will not be paid to the managing general agent until 1 year after they are earned for property insurance business and 5 years after they are earned on casualty business and not until the profits have been verified pursuant to \u00a7 31-1504 . (11) The managing general agent shall not: (A) Bind reinsurance or retrocessions on behalf of the insurer, except that the managing general agent may bind facultative reinsurance contracts pursuant to obligatory facultative agreements if the contract with the insurer contains reinsurance underwriting guidelines including, for both reinsurance assumed and ceded, a list of reinsurers with which such automatic agreements are in effect, the coverages and amounts or percentages that may be reinsured, and commission schedules; (B) Commit the insurer to participate in insurance or reinsurance syndicates; (C) Appoint any producer without assuring that the producer is lawfully licensed to transact the type of insurance for which he is appointed; (D) Without prior approval of the insurer, pay or commit the insurer to pay a claim over a specified amount, net of reinsurance, which shall not exceed 1% of the insurer\u2019s policyholder\u2019s surplus as of December 31 of the last completed calendar year; (E) Collect any payment from a reinsurer or commit the insurer to any claim settlement with a reinsurer without prior approval of the insurer. If prior approval is given, a report must be promptly forwarded to the insurer; (F) Permit its subproducer to serve on the insurer\u2019s board of directors; (G) Jointly employ an individual who is employed with the insurer; or (H) Appoint a submanaging general agent. ( Oct. 21, 1993, D.C. Law 10-41, \u00a7 4, 40 DCR 6014 ; May 16, 1995, D.C. Law 10-255, \u00a7 29(b), 41 DCR 5193 .) Prior Codifications 1981 Ed., \u00a7\u200235-3003. Previous \u00a7 31\u20131502. Licensure. Next \u00a7 31\u20131504. Duties of insurers. The codes and laws on this website are in the public domain. Please do not scrape. Instead, bulk download the HTML or XML . Powered by the non-profit Open Law Library . \u00a7 31\u20131504. Duties of insurers. | D.C. Law Library Skip to main content Toggle mobile menu Navigation D.C. Law Library Code of the District of Columbia Title 31. Insurance and Securities. Chapter 15. Managing General Agents. \u00a7 31\u20131504. Duties of insurers. Code of the District of Columbia \u00a7 31\u20131504. Duties of insurers. (a) The insurer shall have on file an independent financial examination, in a form acceptable to the Mayor, of each managing general agent with which it has done business. (b) If a managing general agent establishes loss reserves, the insurer shall annually obtain the opinion of an actuary attesting to the adequacy of loss reserves established for losses incurred and outstanding on business produced by the managing general agent. This is in addition to any other required loss reserve certification. (c) The insurer shall periodically (at least semiannually) conduct an on-site review of the underwriting and claims processing operations of the managing general agent. (d) Binding authority for all reinsurance contracts or participation in insurance or reinsurance syndicates shall rest with an officer of the insurer, who shall not be affiliated with the managing general agent. (e) Within 30 days of entering into or terminating a contract with a managing general agent, the insurer shall provide written notification of the appointment or termination to the Mayor. Notices of appointment of a managing general agent shall include a statement of duties which the applicant is expected to perform on behalf of the insurer, the lines of insurance for which the applicant is to be authorized to act, and any other information the Mayor may request. (f) An insurer shall review its books and records each quarter to determine if any producer has, because of \u00a7 31-1501(4) , become a managing general agent as defined in that section. If the insurer determines that a producer has become a managing general agent pursuant to the above, the insurer shall promptly notify the producer and the Mayor of the determination, and the insurer and producer shall fully comply with the provisions of this chapter within 30 days. (g) An insurer shall not appoint to its board of directors an officer, director, employee, subproducer, or controlling shareholder of its managing general agents. This subsection shall not apply to relationships governed by Chapter 7 of this title or, if applicable, Chapter 4 of this title . ( Oct. 21, 1993, D.C. Law 10-41, \u00a7 5, 40 DCR 6014 ; May 16, 1995, D.C. Law 10-255, \u00a7 29(c), 41 DCR 5193 .) Prior Codifications 1981 Ed., \u00a7\u200235-3004. Section References This section is referenced in \u00a7 31-1503 . Previous \u00a7 31\u20131503. Required contract provisions. Next \u00a7 31\u20131505. Examination authority. The codes and laws on this website are in the public domain. Please do not scrape. Instead, bulk download the HTML or XML . Powered by the non-profit Open Law Library . \u00a7 31\u20131505. Examination authority. | D.C. Law Library Skip to main content Toggle mobile menu Navigation D.C. Law Library Code of the District of Columbia Title 31. Insurance and Securities. Chapter 15. Managing General Agents. \u00a7 31\u20131505. Examination authority. Code of the District of Columbia \u00a7 31\u20131505. Examination authority. The acts of the managing general agent are considered to be the acts of the insurer on whose behalf it is acting. A managing general agent may be examined as if it were the insurer. ( Oct. 21, 1993, D.C. Law 10-41, \u00a7 6, 40 DCR 6014 .) Prior Codifications 1981 Ed., \u00a7\u200235-3005. Previous \u00a7 31\u20131504. Duties of insurers. Next \u00a7 31\u20131506. Penalties and liabilities. The codes and laws on this website are in the public domain. Please do not scrape. Instead, bulk download the HTML or XML . Powered by the non-profit Open Law Library . \u00a7 31\u20131506. Penalties and liabilities. | D.C. Law Library Skip to main content Toggle mobile menu Navigation D.C. Law Library Code of the District of Columbia Title 31. Insurance and Securities. Chapter 15. Managing General Agents. \u00a7 31\u20131506. Penalties and liabilities. Code of the District of Columbia \u00a7 31\u20131506. Penalties and liabilities. (a) If the Mayor determines that the managing general agent or any other person has not materially complied with this chapter, or any regulation or order promulgated thereunder, after notice and opportunity to be heard, the Mayor may order: (1) For each separate violation, a penalty in an amount not exceeding $10,000, or not more than $25,000 for intentional violations; (2) Revocation or suspension of the producer\u2019s license; and (3) If it was found that because of material noncompliance the insurer has suffered any loss or damage, the Commissioner may maintain a civil action brought by or on behalf of the insurer and its policyholders and creditors for recovery of compensatory damages for the benefit of the insurer and its policyholders and creditors, or other appropriate relief. (b) The decision, determination, or order of the Mayor pursuant to subsection (a) of this section shall be subject to judicial review pursuant to subchapter I of Chapter 5 of Title 2 , \u00a7\u00a7 31-2502.43 [repealed] and 31-2502.44 [repealed], and \u00a7\u00a7 31-4327 [repealed] and 31-4332 . (c) Nothing in this section shall affect the right of the Mayor to impose any other penalties provided in the insurance law of the District. (d) Nothing in this chapter is intended to or shall in any manner limit or restrict the rights of policyholders, claimants, and auditors. ( Oct. 21, 1993, D.C. Law 10-41, \u00a7 7, 40 DCR 6014 ; Apr. 26, 1994, D.C. Law 10-103, \u00a7 5, 41 DCR 1005 .) Prior Codifications 1981 Ed., \u00a7\u200235-3006. Cross References Hospital and medical services corporations, applicable law, see \u00a7 31-3503 . Temporary Legislation For temporary (225 day) amendment of section, see \u00a7\u20025(a) of Insurance Omnibus Temporary Amendment Act of 1993 (D.C. Law 10-76, March 17, 1994, law notification  41 DCR 1626). Previous \u00a7 31\u20131505. Examination authority. Next Chapter 16. Prohibition of Discrimination in the Provision of Insurance on Basis of AIDS Test. The codes and laws on this website are in the public domain. Please do not scrape. Instead, bulk download the HTML or XML . Powered by the non-profit Open Law Library .",
  "metadata": {
    "site_url": "https://code.dccouncil.gov/us/dc/council/code/titles/31/chapters/15",
    "extra_data": {
      "code_title": "Title 31: Insurance and Securities",
      "chapter_number": "15",
      "separated_text": {
        "\u00a7 31\u20131501. Definitions.": "For the purposes of this chapter, the term:",
        "Prior Codifications": "1981 Ed., \u00a7\u200235-3006.",
        "Section References": "This section is referenced in \u00a7 31-1503 .",
        "Editor's Notes": "Mayor authorized to issue rules: Section 8 of D.C. Law 10-41 provided that the Mayor shall, pursuant to subchapter I of Chapter 15 of Title 1 subchapter I of Chapter 5 of Title 2 , 2001 Ed., issue rules to implement the provisions of this chapter.",
        "Delegation of Authority": "Delegation of authority pursuant to D.C. Law 10-41 , the Managing General Agents Act of 1993, see Mayor\u2019s Order 94-54, March 7, 1994 ( 41 DCR 1433).",
        "\u00a7 31\u20131502. Licensure.": "(a) No person, firm, association, or corporation shall act in the capacity of a managing general agent with respect to risks located in the District for an insurer licensed in the District, unless the person is a licensed broker in the District.",
        "\u00a7 31\u20131503. Required contract provisions.": "No person, firm, association, or corporation acting in the capacity of a managing general agent shall place business with an insurer unless there is in force a written contract between the parties which sets forth the responsibilities of each party, and where both parties share responsibility for a particular function, specifies the division of the responsibilities, and which contains the following minimum provisions:",
        "\u00a7 31\u20131504. Duties of insurers.": "(a) The insurer shall have on file an independent financial examination, in a form acceptable to the Mayor, of each managing general agent with which it has done business.",
        "\u00a7 31\u20131505. Examination authority.": "The acts of the managing general agent are considered to be the acts of the insurer on whose behalf it is acting. A managing general agent may be examined as if it were the insurer.",
        "\u00a7 31\u20131506. Penalties and liabilities.": "(a) If the Mayor determines that the managing general agent or any other person has not materially complied with this chapter, or any regulation or order promulgated thereunder, after notice and opportunity to be heard, the Mayor may order:",
        "Cross References": "Hospital and medical services corporations, applicable law, see \u00a7 31-3503 .",
        "Temporary Legislation": "For temporary (225 day) amendment of section, see \u00a7\u20025(a) of Insurance Omnibus Temporary Amendment Act of 1993 (D.C. Law 10-76, March 17, 1994, law notification  41 DCR 1626)."
      }
    }
  }
}