{
  "text": "\u00a7 31\u2013201. Establishment; appointment of Superintendent and clerk. [Repealed] | D.C. Law Library Skip to main content Toggle mobile menu Navigation D.C. Law Library Code of the District of Columbia Title 31. Insurance and Securities. Chapter 2. Duties of Commissioner; Requirements of Industry. \u00a7 31\u2013201. Establishment; appointment of Superintendent and clerk. [Repealed] Code of the District of Columbia \u00a7 31\u2013201. Establishment; appointment of Superintendent and clerk. [Repealed] Repealed. ( May 21, 1997, D.C. Law 11-268, \u00a7 10(c), 44 DCR 1730 .) Prior Codifications 1981 Ed., \u00a7\u200235-101. Section References This section is referenced in \u00a7 31-3503 . Editor's Notes Department of Insurance abolished: The Department of Insurance, including the Superintendent, was abolished and the functions thereof transferred to the Board of Commissioners of the District of Columbia by Reorganization Plan No. 5 of 1952. Reorganization Order No. 43, dated June 23, 1953, as amended, established, under the direction and control of a Commissioner, a Department of Insurance headed by a Superintendent. The Order provided for the organization of the Department, abolished the previously existing Department of Insurance, and provided that all functions and positions of the previous Department would be transferred to the new Department of Insurance, including the duties, powers, and authorities of all officers and employees; and that all personnel, property, records and unexpended balances relating to the functions and positions transferred would also be transferred to the new Department. The executive functions of the Board of Commissioners were transferred to the Commissioner of the District of Columbia by \u00a7\u2002401 of Reorganization Plan No. 3 of 1967. The functions of the Superintendent of Insurance were transferred to the Department of Consumer and Regulatory Affairs by Reorganization Plan No. 1 of 1983, effective March 31, 1983. Pursuant to the provisions of D.C. Law 11- (Act 11-524), the Department of Insurance and Securities Regulation was established and the duties of the Superintendent of Insurance and the Insurance Administration were assumed by the Commissioner of Insurance and Securities, and the Insurance Administration in the Department of Consumer and Regulatory Affairs was abolished. Previous Chapter 2. Duties of Commissioner; Requirements of Industry. Next \u00a7 31\u2013202. General duties of Commissioner; companies or associations to file certain information; service of legal process; rules and regulations. The codes and laws on this website are in the public domain. Please do not scrape. Instead, bulk download the HTML or XML . Powered by the non-profit Open Law Library . \u00a7 31\u2013202. General duties of Commissioner; companies or associations to file certain information; service of legal process; rules and regulations. | D.C. Law Library Skip to main content Toggle mobile menu Navigation D.C. Law Library Code of the District of Columbia Title 31. Insurance and Securities. Chapter 2. Duties of Commissioner; Requirements of Industry. \u00a7 31\u2013202. General duties of Commissioner; companies or associations to file certain information; service of legal process; rules and regulations. Code of the District of Columbia \u00a7 31\u2013202. General duties of Commissioner; companies or associations to file certain information; service of legal process; rules and regulations. (a) It shall be the duty of the Commissioner to see that all laws of the United States relating to insurance or insurance companies, benefit orders, associations, and others doing insurance business in the District are faithfully executed, to keep on file in the Insurance Administration office copies of the charters, declarations of organizations, or articles of incorporation of every company, association, or order doing business in the District. (b) Before any such insurance company, association, or order shall be licensed to do business in the District it shall file with the Commissioner a copy of its charter, declaration of organization, or articles of incorporation duly certified in accordance with the law by the Commissioner of Insurance and Securities [Commissioner of the Department of Insurance, Securities, and Banking], Insurance Commissioner, or other proper officers of the state, territory, or nation where the company, association, group, or organization was organized, a certificate setting forth that it is entitled to transact business and assume risks and issue policies of insurance therein and any other information required by the Commissioner; and a duly executed instrument appointing some suitable person in the District of Columbia, or not 10 miles beyond the territorial limits of the District of Columbia, as the agent for such company, upon whom all lawful process in any action or legal proceeding against it in the District may be served and shall register with the Commissioner the address of its principal office and the name and address of its agent for service of process in the District, including any changes in address. (c) Should said company refuse to appoint such agent, or should any person, after making reasonable efforts to do so (which efforts shall be documented), be unable to serve such agent, said legal process shall be served upon the Commissioner and shall be deemed service upon the company. The Commissioner may by regulation establish fees to be paid when legal process is served upon the Commissioner pursuant to this section. Whenever the Commissioner is served pursuant to this section, he or she shall forward forthwith such process by certified mail to the company named therein, and shall maintain a log showing when such process was served upon the Commissioner and when it was forwarded to the person named therein. The Commissioner shall provide to any person, upon request, the name and address of the agent for any company, or in the alternative, a list of all such agents. (d) Any company, association, group, or organization that fails to comply with the requirements of subsection (b) of this section shall be guilty of a misdemeanor and shall be fined not more than $500 a day for each violation. Civil fines, penalties, and fees may be imposed as alternative sanctions on any company, association, group, or organization that fails to comply with the requirements of subsection (b) of this section, or any rules or regulations issued pursuant to this section. Any company, association, group, or organization against which a fine, penalty, or fee has been imposed may, within 30 days after notice of the penalty is sent, contest the imposition or the amount of the civil fine, penalty, or fee. The hearing shall commence not less than 10 days nor more than 30 days from the date the request for the hearing is received by the Commissioner. The hearing shall be conducted according to the rules for contested cases enumerated in Title 26 (Insurance) of the District of Columbia Municipal Regulations (26 DCMR). (e) The Commissioner shall maintain as confidential any documents or information received from the National Association of Insurance Commissioners or insurance departments of other states which is confidential in such other jurisdictions. The Commissioner may share information, including otherwise confidential information, with the National Association of Insurance Commissioners or insurance departments of other states so long as such other jurisdictions agree to maintain the same level of confidentiality as is available under District of Columbia law. ( Mar. 3, 1901, 31 Stat. 1290, ch. 854, \u00a7 646 ; Jan. 17, 1912, 37 Stat. 53, ch. 11; June 14, 1994, D.C. Law 10-128, \u00a7 404, 41 DCR 2096 ; Mar. 21, 1995, D.C. Law 10-233, \u00a7 2, 42 DCR 24 ; Apr. 18, 1996, D.C. Law 11-110, \u00a7 35, 43 DCR 530 ; May 24, 1996, D.C. Law 11-121, \u00a7 2, 43 DCR 1538 ; May 21, 1997, D.C. Law 11-268, \u00a7 10(d), 44 DCR 1730 ; Mar. 24, 1998, D.C. Law 12-81, \u00a7 19, 45 DCR 745 .) Prior Codifications 1981 Ed., \u00a7\u200235-102. 1973 Ed., \u00a7\u200235-102. Section References This section is referenced in \u00a7 31-501 , \u00a7 31-1802 , \u00a7 31-2502.22 , \u00a7 31-3503 , \u00a7 31-3931.11 , \u00a7 31-4103 , \u00a7 31-4107 , \u00a7 31-4446 , \u00a7 31-4501 , and \u00a7 31-5201 . Cross References Certificate of authority of fire, casualty, or marine insurance company, revocation or suspension, see \u00a7 31-2502.03 . Domestic ceding insurers, compliance with this section, see \u00a7 31-501 . Election to convert stock company to mutual company, rules and regulations governing, see \u00a7 31-4419 . Failure of domestic company to keep books, records, and files within District, effect, see \u00a7 31-5204 . Failure to file annual statements, effect, see \u00a7 47-2607 . Foreign and alien life companies, proof of compliance with this section, see \u00a7 31-4501 . Foreign or alien fire, casualty and marine insurers, proof of compliance with this section, see \u00a7 31-2502.22 . Hospital and medical services corporation, proof of compliance with this section, see \u00a7 31-3503 . Insurance under Employees\u2019 Compensation Act, see \u00a7 31-5205 . Licenses for insurance companies, see \u00a7 47-2603 . Life and fire insurance, compliance with this section, see \u00a7 31-5201 . Merger or consolidation, foreign and domestic companies, agent for service of process, see \u00a7 31-4446 . Organization permits of domestic life companies, revocation or suspension, see \u00a7 31-4406 . Reinsurance intermediary, compliance with this section, see \u00a7 31-1802 . Revocation or suspension of license or certificate of authority of life insurance companies, see \u00a7 31-4305 . Revocation or suspension of permit for impairment of capital, see \u00a7 31-5202 . Risk retention groups doing business in district not chartered in district, compliance with requirements of this section, see \u00a7 31-4103 . Risk retention purchasing groups, proof of compliance with this section, see \u00a7 31-4107 . Editor's Notes Department of Insurance abolished: See Historical and Statutory Notes following \u00a7 31-201 . Previous \u00a7 31\u2013201. Establishment; appointment of Superintendent and clerk. [Repealed] Next \u00a7 31\u2013203. Required annual financial statements of companies or associations \u2014 Contents; publication. [Repealed] The codes and laws on this website are in the public domain. Please do not scrape. Instead, bulk download the HTML or XML . Powered by the non-profit Open Law Library . \u00a7 31\u2013203. Required annual financial statements of companies or associations \u2014 Contents; publication. [Repealed] | D.C. Law Library Skip to main content Toggle mobile menu Navigation D.C. Law Library Code of the District of Columbia Title 31. Insurance and Securities. Chapter 2. Duties of Commissioner; Requirements of Industry. \u00a7 31\u2013203. Required annual financial statements of companies or associations \u2014 Contents; publication. [Repealed] Code of the District of Columbia \u00a7 31\u2013203. Required annual financial statements of companies or associations \u2014 Contents; publication. [Repealed] Repealed. ( Oct. 21, 1993, D.C. Law 10-42, \u00a7 7(a), 40 DCR 6020 .) Prior Codifications 1981 Ed., \u00a7\u200235-103. Section References This section is referenced in \u00a7 31-4901 . Previous \u00a7 31\u2013202. General duties of Commissioner; companies or associations to file certain information; service of legal process; rules and regulations. Next \u00a7 31\u2013204. Required annual financial statements of companies or associations \u2014 Foreign companies or associations. The codes and laws on this website are in the public domain. Please do not scrape. Instead, bulk download the HTML or XML . Powered by the non-profit Open Law Library . \u00a7 31\u2013204. Required annual financial statements of companies or associations \u2014 Foreign companies or associations. | D.C. Law Library Skip to main content Toggle mobile menu Navigation D.C. Law Library Code of the District of Columbia Title 31. Insurance and Securities. Chapter 2. Duties of Commissioner; Requirements of Industry. \u00a7 31\u2013204. Required annual financial statements of companies or associations \u2014 Foreign companies or associations. Code of the District of Columbia \u00a7 31\u2013204. Required annual financial statements of companies or associations \u2014 Foreign companies or associations. The financial statements of insurance companies or associations, required hereby to be filed annually with the Commissioner of Insurance and Securities [Commissioner of the Department of Insurance, Securities, and Banking], shall set forth specifically the assets, liabilities, and conduct of the affairs within the United States of companies or associations organized outside of the territorial limits of the United States, and such statement shall be verified under oath by the manager and assistant manager or other proper officers of such companies or associations within the United States; and so much of this chapter as requires the publication of annual statements shall only extend to the statements respecting the affairs of such foreign companies or associations within the United States. ( Mar. 3, 1901, 31 Stat. 1291, ch. 854, \u00a7 649 ; May 21, 1997, D.C. Law 11-268, \u00a7 10(d), 44 DCR 1730 .) Prior Codifications 1981 Ed., \u00a7\u200235-104. 1973 Ed., \u00a7\u200235-104. Cross References Annual statements and taxes, see \u00a7 31-5202 . Taxation and fiscal affairs of insurance companies, see \u00a7 47-2601 et seq. Editor's Notes Department of Insurance abolished: See Historical and Statutory Notes following \u00a7 31-201 . Previous \u00a7 31\u2013203. Required annual financial statements of companies or associations \u2014 Contents; publication. [Repealed] Next \u00a7 31\u2013205. Required annual statement of business; tax payments; annuities exemption. The codes and laws on this website are in the public domain. Please do not scrape. Instead, bulk download the HTML or XML . Powered by the non-profit Open Law Library . \u00a7 31\u2013205. Required annual statement of business; tax payments; annuities exemption. | D.C. Law Library Skip to main content Toggle mobile menu Navigation D.C. Law Library Code of the District of Columbia Title 31. Insurance and Securities. Chapter 2. Duties of Commissioner; Requirements of Industry. \u00a7 31\u2013205. Required annual statement of business; tax payments; annuities exemption. Code of the District of Columbia \u00a7 31\u2013205. Required annual statement of business; tax payments; annuities exemption. (a) Every insurance company and association doing business in the District of Columbia shall, through its local agents or representatives, furnish to the Commissioner, during the month of January of each year, a statement of its business in the District, setting forth specifically the net amount of its premium receipts, the amount of losses paid, the amount of expenses incurred, respecting the business done in the District during the calendar year next preceding, and the Commissioner shall preserve a separate record of the same in his office for convenient reference, showing the ratio of such losses and expenses, respectively, to the premium receipts. (b) Every insurance company or association of whatever kind or character, not including fraternal beneficiary associations, shall, as required by law, pay to the Director of the Department of Finance and Revenue, or to a depository designated by the Director, in lieu of all other taxes, except taxes upon real estate and any license fees provided for in \u00a7 31-804 [repealed] an amount equal to the following: (1) (A) One and seven tenths percent of the gross amount of premiums received during the preceding calendar year by every life insurance company or association, not including fraternal beneficiary associations, or the gross payments or deposits collected from holders of fraternal beneficiary association certificates, on contracts of insurance covering risks resident in the District during the preceding year, including contracts for group insurance and annuities and without including or deducting any amounts received or paid for reinsurance. (B) In determining the gross amount of premiums to be taxed, there shall be excluded all premiums received from policies or contracts issued in connection with a pension, annuity, profit-sharing plan or individual retirement annuity qualified or exempt under \u00a7\u00a7\u2002401, 403, 404, 408, or 501(a) of the Internal Revenue Code, or successor provisions, and all premiums returned to policyholders or annuitants during the preceding calendar year, except cash surrender values, all dividends that, during the year, have been paid in cash or applied in reduction of premiums or left to accumulate to the credit of policyholders or annuitants. (C) In determining the gross amount of premiums to be taxed, there shall be excluded all consideration received in connection with an annuity contract whether or not such contract is qualified or exempt under the Internal Revenue Code, and all premiums returned to policyholders or annuitants during the preceding calendar year, except cash surrender values, and all dividends that, during said year, have been paid in cash or applied in reduction of premiums or left to accumulate to the credit of policyholders or annuitants. (2) One and seven tenths percent of the gross amount of premiums, assessments, and fees received during the preceding calendar year by every company or association other than life on contracts of insurance other than life for business done in the District, after deducting the amount returned upon canceled policies, certificates, and rejected applications. (3) Except as provided in paragraph (4) of this subsection, the premium tax shall be paid on or before March 1 of the year following the calendar year for which the tax is due.  The Commissioner may suspend or revoke the license of a company or association that fails to pay premium tax on or before the due date. (4) Each insurance company and association transacting business in the District whose District premium tax liability for the preceding calendar year was $1,000 or more shall remit on or before June 1, on a prepayment basis, an amount equal to one-half of the premium tax liability for the preceding calendar year.  The sums prepaid by a company or association under this subsection shall be allowed as credits against its premium tax liability for the calendar year during which the payments are made.  If a prepayment made under this subsection exceeds the annual premium tax liability, the excess shall be allowed as a credit against subsequent prepayment or tax liabilities.  The Commissioner may suspend or revoke the license of a company or association that fails to make a prepayment on or before the due date. (c) A hospital service corporation or medical service corporation may deduct, up to $550,000, the corporation\u2019s payment to the rate stabilization fund under \u00a7 31-3514 and payments and expenditures pursuant to a public-private partnership entered into in accordance with Chapter 35 of this title from the amount otherwise due by the corporation under subsection (b) of this section. (d) The Commissioner shall determine whether or not the tax remitted is correct. If the tax remitted is not sufficient, the Commissioner shall notify the delinquent company of the amount of such delinquency and certify the amount thereof to the Department of Finance and Revenue which shall proceed to collect such delinquency. (e) An insurer may offset an assessment made pursuant to \u00a7 31-5406 (\u201cLife and Health Insurance Guaranty Association Act\u201d), against its premium tax liability pursuant to \u00a7 31-5410 to the extent of 10% of the amount of the assessment for each of the 10 calendar years following the year in which the assessment was paid.  If an insurer ceases doing business, all uncredited assessments may be credited against its premium tax liability for the year it ceases doing business. (f) (1) When by the laws of any other jurisdiction a premium or income or other taxes, or fees, fines, penalties, licenses, deposit requirement, or other obligations, prohibitions or restrictions are imposed upon District domestic insurance companies doing business in the other jurisdiction, or upon the agents of District companies, which in the aggregate are in excess of the aggregate of the taxes, fees, fines, penalties, licenses, deposit requirements or other obligations, prohibitions or restrictions directly imposed upon insurance companies of the other jurisdiction under the statutes of the District, the same obligations, prohibitions or restrictions for whatever kind are in the same manner and for the same purpose imposed upon insurance companies of the other jurisdiction doing business in the District. (2) Insurance premium taxes paid which were not paid under protest shall not be refunded if the refund claim is based upon an alleged error or mistake of law or erroneous interpretation of statute regarding the validity or legality of this section under the laws or constitution of the United States. (3) For the purpose of this section, an alien insurer is deemed domiciled in a United States jurisdiction designated by it wherein it has established its principal office or agency in the United States, maintains the largest amount of its assets held in trust or on deposit for the security of its policyholders or policyholders and creditors in the United States, or in which it was admitted to do business in the United States. (4) This section does not apply to ad valorem taxes on real or personal property or to personal income taxes. ( Mar. 3, 1901, 31 Stat. 1291, ch. 854, \u00a7 650 ; June 30, 1902, 32 Stat. 534, ch. 1329; May 21, 1997, D.C. Law 11-268, 44 DCR 1730 ; Apr. 29, 1998, D.C. Law 12-86, \u00a7 201, 45 DCR 1172 ; Mar. 2, 2007, D.C. Law 16-192, \u00a7 5013(a), 53 DCR 6899 ; Feb. 4, 2010, D.C. Law 18-104, \u00a7 4(a), 56 DCR 9182 ; Sept. 24, 2010, D.C. Law 18-223, \u00a7 2182, 57 DCR 6242 .) Prior Codifications 1981 Ed., \u00a7\u200235-105. 1973 Ed., \u00a7\u200235-105. Section References This section is referenced in \u00a7 31-3514 , \u00a7 31-5231 , and \u00a7 31-5233 . Effect of Amendments D.C. Law 16-192 , in subsec. (b), deleted \u201cand nonprofit hospital and medical service corporations\u201d following \u201cbeneficiary associations\u201d; and rewrote subsec. (c) which had read as follows: \u201c(c) Notwithstanding section 105, a hospital service corporation, medical service corporation, pharmaceutical service corporation, optometric service corporation and any other health service corporation shall pay as taxes to the director of the Department of Finance and Revenue an amount equal to 1% of the gross amount of payments received during the preceding calendar year for subscriber contracts covering residents in the District after deducting the amounts returned to subscribers upon canceled subscriber contracts and rejected applications.\u201d D.C. Law 18-104 , in subsec. (c), substituted \u201cpayment to the rate stabilization fund under \u00a7 31-3514 , and payments and expenditures pursuant to a public-private partnership entered into in accordance with Chapter 35 of this title,\u201d for \u201cpayment to the rate stabilization fund under \u00a7 31-3514 ,\u201d. D.C. Law 18-223 , in subsecs. (b)(1A) and (2), substituted \u201cTwo\u201d for \u201cOne and seven tenths\u201d. Cross References Annual statements and taxes, see \u00a7 31-5202 . Insurance companies, taxation and fiscal affairs, see \u00a7 47-2601 et seq. Liability for failure to pay tax, see \u00a7 47-2609 . Retaliatory charges against certain insurance companies, see \u00a7 47-2610 . Emergency Legislation For temporary (90 day) amendment of section, see \u00a7\u20025013(a) of Fiscal Year 2007 Budget Support Emergency Act of 2006 (D.C. Act 16-477, August 8, 2006,  53 DCR 7068). For temporary (90 day) amendment of section, see \u00a7\u20025013(a) of Fiscal Year 2007 Budget Support Congressional Review Emergency Act of 2006 (D.C. Act 16-499, October 23, 2006,  53 DCR 8845). For temporary (90 day) amendment of section, see \u00a7\u20025013(a) of Fiscal Year 2007 Budget Support Congressional Review Emergency Act of 2007 (D.C. Act 17-1, January 16, 2007,  54 DCR 1165). For temporary (90 day) amendment of section, see \u00a7\u20024(a) of Hospital and Medical Services Corporation Regulatory Emergency Amendment Act of 2009 (D.C. Act 18-277, January 11, 2010,  57 DCR 935). For temporary (90 day) amendment of section, see \u00a7\u20022182 of Fiscal Year 2011 Budget Support Emergency Act of 2010 (D.C. Act 18-463, July 2, 2010,  57 DCR 6542). Temporary Legislation For temporary (225 day) amendment of section, see \u00a7\u20024(a) of the Hospital and Medical Services Corporation Regulatory Temporary Amendment Act of 2010 (D.C. Law 18-134, March 23, 2010, law notification  57 DCR 3373). References in Text \u201c Sections 401,  403,  404,  408, and  501(a) of the Internal Revenue Code,\u201d referred to in (b)(1)(B), are codified at  26 U.S.C. \u00a7\u00a7\u2002401,  403,  404,  408, and  501(a), respectively. Pursuant to the Office of the Chief Financial Officer\u2019s \u201cNotice of Public Interest\u201d published in the April 18, 1997, issue of the District of Columbia Register ( 44 DCR 2345) the Office of Tax and Revenue assumed all of the duties and functions previously performed by the Department of Finance and Revenue, as set forth in Commissioner\u2019s Order 69-96, dated March 7, 1969. This action was made effective January 22, 1997, nunc pro tunc. Editor's Notes Application of Law 12-86: Section 203 of D.C. Law 12-86 provided that the provisions of title II of the act shall be applicable to premiums received during the calendar year beginning Jan. 1, 1998, and subsequent years. Office of Collector of Taxes abolished: The Office of the Collector of Taxes was abolished and the functions thereof transferred to the Board of Commissioners of the District of Columbia by Reorganization Plan No. 5 of 1952. All functions of the Office of the Collector of Taxes including the functions of all officers, employees, and subordinate agencies were transferred to the Director, Department of General Administration by Reorganization Order No. 3, dated August 28, 1952. Reorganization Order No. 20, dated November 10, 1952, transferred the functions of the Collector of Taxes to the Finance Office. The same Order provided for the Office of the Collector of Taxes headed by a Collector in the Finance Office, and abolished the previously existing Office of the Collector of Taxes. Reorganization Order No. 20 was superseded and replaced by Organization Order No. 121, dated December 12, 1957, which provided that the Finance Office (consisting of the Office of the Finance Officer, Property Tax Division, Revenue Division, Treasury Division, Accounting Division, and Data Processing Division) would continue under the direction and control of the Director of General Administration, and that the Treasury Division would perform the function of collecting revenues of the District of Columbia and depositing the same with the Treasurer of the United States. Organization Order No. 121 was revoked by Organization Order No. 3, dated December 13, 1967, Part IVC of which prescribed the functions of the Finance Office within a newly established Department of General Administration. The executive functions of the Board of Commissioners were transferred to the Commissioner of the District of Columbia by \u00a7\u2002401 of Reorganization Plan No. 3 of 1967. Functions of the Finance Office as stated in Part IVC of Organization Order No. 3 were transferred to the Director of the Department of Finance and Revenue by Commissioner\u2019s Order No. 69-96, dated March 7, 1969. The collection functions of the Director of the Department of Finance and Revenue were transferred to the District of Columbia Treasurer by \u00a7 47-316 on March 5, 1981. Department of Insurance abolished: See Historical and Statutory Notes following \u00a7 31-201 . For temporary delay until Jan. 1, 1999, of the applicability of D.C. Law 12-86 , as stated in \u00a7\u2002203 of the Omnibus Regulatory Reform Amendment Act of 1998 ( D.C. Law 12-86 ), see \u00a7\u2002502 of the Health Insurance Portability and Accountability Federal Law Conformity, Motor Vehicle Insurance, Regulatory Reform, and Consumer Law Temporary Amendment Act of 1998 ( D.C. Law 12-154 , \u00a7\u2002502). Section 601(b) of D.C. Law 12-154 provided that the act shall expire after 225 days of its having taken effect. For temporary delay of the provisions of \u00a7\u2002203 of the Omnibus Regulatory Reform Amendment Act of 1998 ( D.C. Law 12-86 ), see \u00a7\u2002502 of the Health Insurance Portability and Accountability Federal Law Conformity Emergency Amendment Act of 1998 (D.C. Act 12-339, May 4, 1998,  45 DCR 2947). Section 2184 of D.C. Law 18-223 provided: \u201cSunset. This subtitle shall expire on September 30, 2015.\u201d Previous \u00a7 31\u2013204. Required annual financial statements of companies or associations \u2014 Foreign companies or associations. Next \u00a7 31\u2013206. Required annual reports of Commissioner \u2014 Contents. The codes and laws on this website are in the public domain. Please do not scrape. Instead, bulk download the HTML or XML . Powered by the non-profit Open Law Library . \u00a7 31\u2013206. Required annual reports of Commissioner \u2014 Contents. | D.C. Law Library Skip to main content Toggle mobile menu Navigation D.C. Law Library Code of the District of Columbia Title 31. Insurance and Securities. Chapter 2. Duties of Commissioner; Requirements of Industry. \u00a7 31\u2013206. Required annual reports of Commissioner \u2014 Contents. Code of the District of Columbia \u00a7 31\u2013206. Required annual reports of Commissioner \u2014 Contents. The Commissioner of Insurance and Securities [Commissioner of the Department of Insurance, Securities, and Banking] shall report annually to the Mayor of the District, on or before the 31st day of March, the financial condition of each insurance company and association doing business in said District, as of the 31st day of December next preceding. ( Mar. 3, 1901, 31 Stat. 1292, ch. 854, \u00a7 651 ; May 21, 1997, D.C. Law 11-268, \u00a7 10(d), 44 DCR 1730 .) Prior Codifications 1981 Ed., \u00a7\u200235-106. 1973 Ed., \u00a7\u200235-106. Section References This section is referenced in \u00a7 31-3503 . Cross References Hospital and medical services corporations, applicability of this section, see \u00a7 31-3503 . Editor's Notes Department of Insurance abolished: See Historical and Statutory Notes following \u00a7 35-101 . Change in Government This section originated at a time when local government powers were delegated to a Board of Commissioners of the District of Columbia (see Acts Relating to the Establishment of the District of Columbia and its Various Forms of Governmental Organization in Volume 1). Section 401 of Reorganization Plan No. 3 of 1967 (see Reorganization Plans in Volume 1) transferred all of the functions of the Board of Commissioners under this section to a single Commissioner. The District of Columbia Self-Government and Governmental Reorganization Act, 87 Stat. 818, \u00a7\u2002711 ( D.C. Code, \u00a7 1-207.11 ), abolished the District of Columbia Council and the Office of Commissioner of the District of Columbia. These branches of government were replaced by the Council of the District of Columbia and the Office of Mayor of the District of Columbia, respectively. Accordingly, and also pursuant to \u00a7\u2002714(a) of such Act ( D.C. Code, \u00a7 1-207.14(a) ), appropriate changes in terminology were made in this section. Previous \u00a7 31\u2013205. Required annual statement of business; tax payments; annuities exemption. Next \u00a7 31\u2013207. Required annual reports of Commissioner \u2014 Publication and distribution. The codes and laws on this website are in the public domain. Please do not scrape. Instead, bulk download the HTML or XML . Powered by the non-profit Open Law Library . \u00a7 31\u2013207. Required annual reports of Commissioner \u2014 Publication and distribution. | D.C. Law Library Skip to main content Toggle mobile menu Navigation D.C. Law Library Code of the District of Columbia Title 31. Insurance and Securities. Chapter 2. Duties of Commissioner; Requirements of Industry. \u00a7 31\u2013207. Required annual reports of Commissioner \u2014 Publication and distribution. Code of the District of Columbia \u00a7 31\u2013207. Required annual reports of Commissioner \u2014 Publication and distribution. After May 18, 1910, the annual reports of the Commissioner of Insurance and Securities [Commissioner of the Department of Insurance, Securities, and Banking] shall be printed and bound in 1 volume, and shall be ready for distribution not later than the 1st day of the next regular session of Congress thereafter. ( May 18, 1910, 36 Stat. 379, ch. 248, \u00a7 1 ; May 21, 1997, D.C. Law 11-268, \u00a7 10(e), 44 DCR 1730 .) Prior Codifications 1981 Ed., \u00a7\u200235-107. 1973 Ed., \u00a7\u200235-107. Section References This section is referenced in \u00a7 31-3503 . Cross References Hospital and medical services corporations, applicability of this section, see \u00a7 31-3503 . Temporary Legislation For temporary (225 days) tolling of deadlines under commercial insurance policies during a public health emergency, see \u00a7 2 of Commercial Insurance Claim Tolling Temporary Act of 2021 (D.C. Law 24-19, July 29, 2021, 68 DCR 006023) . For temporary (225 days) tolling of deadlines under commercial insurance policies during a public health emergency, see \u00a7 2 of Commercial Insurance Claim Tolling Emergency Act of 2021 (D.C. Act 24-82, May 25, 2021, 68 DCR 005821) . For temporary (225 days) tolling of deadlines under commercial insurance policies during a public health emergency, see \u00a7 2 of Commercial Insurance Claim Tolling Congressional Review Emergency Act of 2020 (D.C. Act 23-427, Oct. 24, 2020, 67 DCR 12969) . For temporary (225 days) tolling of deadlines under commercial insurance policies during a public health emergency, see \u00a7 2 of Commercial Insurance Claim Tolling Temporary Act of 2020 (D.C. Law 23-143, Oct. 20, 2020, 67 DCR 9912) . For temporary (225 days) tolling of deadlines under commercial insurance policies during a public health emergency, see \u00a7 2 of Commercial Insurance Claim Tolling Emergency Act of 2020 (D.C. Act 23-343, July 27, 2020, 67 DCR 9379) . Editor's Notes Department of Insurance abolished: See Historical and Statutory Notes following \u00a7 31-201 . Previous \u00a7 31\u2013206. Required annual reports of Commissioner \u2014 Contents. Next \u00a7 31\u2013208. Capital requirements of companies or associations. The codes and laws on this website are in the public domain. Please do not scrape. Instead, bulk download the HTML or XML . Powered by the non-profit Open Law Library . \u00a7 31\u2013208. Capital requirements of companies or associations. | D.C. Law Library Skip to main content Toggle mobile menu Navigation D.C. Law Library Code of the District of Columbia Title 31. Insurance and Securities. Chapter 2. Duties of Commissioner; Requirements of Industry. \u00a7 31\u2013208. Capital requirements of companies or associations. Code of the District of Columbia \u00a7 31\u2013208. Capital requirements of companies or associations. It shall be the duty of the said Commissioner of Insurance and Securities [Commissioner of the Department of Insurance, Securities, and Banking] to ascertain whether the capital required by law or the charter of each insurance company or association organized under the laws of the District of Columbia has been actually paid up in cash and is held by its board of directors subject to their control, according to the provisions of their charter, or has been invested in property worth not less than the full amount of the capital stock required by its charter; or, if a mutual company, that it has received and is in actual possession of securities, as the case may be, to the full extent of the value required by its charter; and the president and secretary of such company or association shall make a declaration under oath to said Commissioner, who is hereby empowered to administer oaths when hereby required, that the tangible assets exhibited to him represent bona fide the property of the company or association, which sworn declaration shall be filed and preserved in the office of said Commissioner; and any such officer swearing falsely in regard to any of the provisions hereof shall be deemed guilty of perjury and shall be subject to all the penalties prescribed by law in the District of Columbia for that crime. ( Mar. 3, 1901, 31 Stat. 1292, ch. 854, \u00a7 652 ; May 21, 1997, D.C. Law 11-268, \u00a7 10(d), 44 DCR 1730 .) Prior Codifications 1981 Ed., \u00a7\u200235-108. 1973 Ed., \u00a7\u200235-108. Cross References Capital stock requirements, see \u00a7 31-5202 . Impairment of capital, see \u00a7 31-5201 . Inspection and examination of insurance companies, see \u00a7\u00a7 31-5201 and 31-5202 . Editor's Notes Department of Insurance abolished: See Historical and Statutory Notes following \u00a7 31-201 . Previous \u00a7 31\u2013207. Required annual reports of Commissioner \u2014 Publication and distribution. Next Chapter 2A. Unauthorized Entities. The codes and laws on this website are in the public domain. Please do not scrape. Instead, bulk download the HTML or XML . Powered by the non-profit Open Law Library .",
  "metadata": {
    "site_url": "https://code.dccouncil.gov/us/dc/council/code/titles/31/chapters/2",
    "extra_data": {
      "code_title": "Title 31: Insurance and Securities",
      "chapter_number": "2",
      "separated_text": {
        "\u00a7 31\u2013201. Establishment; appointment of Superintendent and clerk. [Repealed]": "Repealed.",
        "Prior Codifications": "1981 Ed., \u00a7\u200235-108.",
        "Section References": "This section is referenced in \u00a7 31-3503 .",
        "Editor's Notes": "Department of Insurance abolished: See Historical and Statutory Notes following \u00a7 31-201 .",
        "\u00a7 31\u2013202. General duties of Commissioner; companies or associations to file certain information; service of legal process; rules and regulations.": "(a) It shall be the duty of the Commissioner to see that all laws of the United States relating to insurance or insurance companies, benefit orders, associations, and others doing insurance business in the District are faithfully executed, to keep on file in the Insurance Administration office copies of the charters, declarations of organizations, or articles of incorporation of every company, association, or order doing business in the District.",
        "Cross References": "Capital stock requirements, see \u00a7 31-5202 .",
        "\u00a7 31\u2013203. Required annual financial statements of companies or associations \u2014 Contents; publication. [Repealed]": "Repealed.",
        "\u00a7 31\u2013204. Required annual financial statements of companies or associations \u2014 Foreign companies or associations.": "The financial statements of insurance companies or associations, required hereby to be filed annually with the Commissioner of Insurance and Securities [Commissioner of the Department of Insurance, Securities, and Banking], shall set forth specifically the assets, liabilities, and conduct of the affairs within the United States of companies or associations organized outside of the territorial limits of the United States, and such statement shall be verified under oath by the manager and assistant manager or other proper officers of such companies or associations within the United States; and so much of this chapter as requires the publication of annual statements shall only extend to the statements respecting the affairs of such foreign companies or associations within the United States.",
        "\u00a7 31\u2013205. Required annual statement of business; tax payments; annuities exemption.": "(a) Every insurance company and association doing business in the District of Columbia shall, through its local agents or representatives, furnish to the Commissioner, during the month of January of each year, a statement of its business in the District, setting forth specifically the net amount of its premium receipts, the amount of losses paid, the amount of expenses incurred, respecting the business done in the District during the calendar year next preceding, and the Commissioner shall preserve a separate record of the same in his office for convenient reference, showing the ratio of such losses and expenses, respectively, to the premium receipts.",
        "Effect of Amendments": "D.C. Law 16-192 , in subsec. (b), deleted \u201cand nonprofit hospital and medical service corporations\u201d following \u201cbeneficiary associations\u201d; and rewrote subsec. (c) which had read as follows: \u201c(c) Notwithstanding section 105, a hospital service corporation, medical service corporation, pharmaceutical service corporation, optometric service corporation and any other health service corporation shall pay as taxes to the director of the Department of Finance and Revenue an amount equal to 1% of the gross amount of payments received during the preceding calendar year for subscriber contracts covering residents in the District after deducting the amounts returned to subscribers upon canceled subscriber contracts and rejected applications.\u201d",
        "Emergency Legislation": "For temporary (90 day) amendment of section, see \u00a7\u20025013(a) of Fiscal Year 2007 Budget Support Emergency Act of 2006 (D.C. Act 16-477, August 8, 2006,  53 DCR 7068).",
        "Temporary Legislation": "For temporary (225 days) tolling of deadlines under commercial insurance policies during a public health emergency, see \u00a7 2 of Commercial Insurance Claim Tolling Temporary Act of 2021 (D.C. Law 24-19, July 29, 2021, 68 DCR 006023) .",
        "References in Text": "\u201c Sections 401,  403,  404,  408, and  501(a) of the Internal Revenue Code,\u201d referred to in (b)(1)(B), are codified at  26 U.S.C. \u00a7\u00a7\u2002401,  403,  404,  408, and  501(a), respectively.",
        "\u00a7 31\u2013206. Required annual reports of Commissioner \u2014 Contents.": "The Commissioner of Insurance and Securities [Commissioner of the Department of Insurance, Securities, and Banking] shall report annually to the Mayor of the District, on or before the 31st day of March, the financial condition of each insurance company and association doing business in said District, as of the 31st day of December next preceding.",
        "Change in Government": "This section originated at a time when local government powers were delegated to a Board of Commissioners of the District of Columbia (see Acts Relating to the Establishment of the District of Columbia and its Various Forms of Governmental Organization in Volume 1). Section 401 of Reorganization Plan No. 3 of 1967 (see Reorganization Plans in Volume 1) transferred all of the functions of the Board of Commissioners under this section to a single Commissioner. The District of Columbia Self-Government and Governmental Reorganization Act, 87 Stat. 818, \u00a7\u2002711 ( D.C. Code, \u00a7 1-207.11 ), abolished the District of Columbia Council and the Office of Commissioner of the District of Columbia. These branches of government were replaced by the Council of the District of Columbia and the Office of Mayor of the District of Columbia, respectively. Accordingly, and also pursuant to \u00a7\u2002714(a) of such Act ( D.C. Code, \u00a7 1-207.14(a) ), appropriate changes in terminology were made in this section.",
        "\u00a7 31\u2013207. Required annual reports of Commissioner \u2014 Publication and distribution.": "After May 18, 1910, the annual reports of the Commissioner of Insurance and Securities [Commissioner of the Department of Insurance, Securities, and Banking] shall be printed and bound in 1 volume, and shall be ready for distribution not later than the 1st day of the next regular session of Congress thereafter.",
        "\u00a7 31\u2013208. Capital requirements of companies or associations.": "It shall be the duty of the said Commissioner of Insurance and Securities [Commissioner of the Department of Insurance, Securities, and Banking] to ascertain whether the capital required by law or the charter of each insurance company or association organized under the laws of the District of Columbia has been actually paid up in cash and is held by its board of directors subject to their control, according to the provisions of their charter, or has been invested in property worth not less than the full amount of the capital stock required by its charter; or, if a mutual company, that it has received and is in actual possession of securities, as the case may be, to the full extent of the value required by its charter; and the president and secretary of such company or association shall make a declaration under oath to said Commissioner, who is hereby empowered to administer oaths when hereby required, that the tangible assets exhibited to him represent bona fide the property of the company or association, which sworn declaration shall be filed and preserved in the office of said Commissioner; and any such officer swearing falsely in regard to any of the provisions hereof shall be deemed guilty of perjury and shall be subject to all the penalties prescribed by law in the District of Columbia for that crime."
      }
    }
  }
}